CHANGELOG.txt
LICENSE.txt
MANIFEST.in
README.txt
setup.cfg
setup.py
larkinlab/__init__.py
larkinlab.egg-info/PKG-INFO
larkinlab.egg-info/SOURCES.txt
larkinlab.egg-info/dependency_links.txt
larkinlab.egg-info/requires.txt
larkinlab.egg-info/top_level.txt
larkinlab/explore/__init__.py
larkinlab/machinelearning/__init__.py