Metadata-Version: 2.1
Name: larkinlab
Version: 0.0.18
Summary: A collection of code assembled to help streamline things. For Data Analysis.
Home-page: UNKNOWN
Author: Conor Larkin
Author-email: conor.larkin16@gmail.com
License: MIT
Keywords: data
Platform: UNKNOWN
Classifier: Development Status :: 5 - Production/Stable
Classifier: Intended Audience :: Developers
Classifier: Operating System :: Microsoft :: Windows :: Windows 10
Classifier: License :: OSI Approved :: MIT License
Classifier: Programming Language :: Python :: 3
